{"d035bde8-d20b-4d33-b3ac-29fc35572975": {"id": "d035bde8-d20b-4d33-b3ac-29fc35572975", "topic": "Ogey Calibur - Day 1 - Group 1 Winner", "open": false, "winOption": 1, "totalPool": 16085000000, "closingTime": 1715349600000, "options": [{"optionid": 0, "option": "Avtism - [/hfz/, /vtwbg/, /nasfaqg/, /fig/, /news/]"}, {"optionid": 1, "option": "M.A.A.Y.B. - [/mans/, /stars/, /haha/, /mint/, /yamu/] "}], "userBets": {"0": [{"userid": "d151de00-6642-4807-8db7-615be63c0103", "username": "skeleturtle-2", "betAmount": 50000000, "option": 0}, {"userid": "55b4cbff-bbe8-4061-9ff2-194f53868401", "username": "The Tampa Bay Buccaneers", "betAmount": 5000000000, "option": 0}, {"userid": "8b16c5d9-1d06-467c-9c85-eea8d4bf7f68", "username": "Takoside", "betAmount": 5000000000, "option": 0}, {"userid": "e2f158e4-b22e-4562-9236-a11aab56c20e", "username": "TFRBATTLERISGAY", "betAmount": 5000000, "option": 0}, {"userid": "726b5a5e-9dc0-438e-b6be-fb901a51f482", "username": "Bombshell Blondes Banking", "betAmount": 500000000, "option": 0}], "1": [{"userid": "708be5de-6f82-4353-8d4c-892c1626512e", "username": "IKZ", "betAmount": 30000000, "option": 1}, {"userid": "463fc6c2-201d-4dbc-a35b-0e6960c2ec89", "username": "AltoWalker", "betAmount": 5000000000, "option": 1}, {"userid": "726b5a5e-9dc0-438e-b6be-fb901a51f482", "username": "Bombshell Blondes Banking", "betAmount": 500000000, "option": 1}]}}, "ce3a03cb-3d63-4618-893a-d23449fb1d51": {"id": "ce3a03cb-3d63-4618-893a-d23449fb1d51", "topic": "Ogey Calibur - Day 1 - Group 2 Winner", "open": false, "winOption": 1, "totalPool": 11565000000, "closingTime": 1715353200000, "options": [{"optionid": 0, "option": "Special Needs Unit - [/vrt/, /tactical/, /pyon/, /choc/, /vsinger/]"}, {"optionid": 1, "option": "Phase Coffee - [/jong/, Lia From Phase Connect, /pcgia/, /pcgen3k/, /fvr/]"}], "userBets": {"0": [{"userid": "8b16c5d9-1d06-467c-9c85-eea8d4bf7f68", "username": "Takoside", "betAmount": 5000000000, "option": 0}, {"userid": "e2f158e4-b22e-4562-9236-a11aab56c20e", "username": "TFRBATTLERISGAY", "betAmount": 5000000, "option": 0}, {"userid": "79c5aa12-d3e9-49aa-9b63-5cd3bb5c7e33", "username": "BeerSalad", "betAmount": 10000000, "option": 0}], "1": [{"userid": "55b4cbff-bbe8-4061-9ff2-194f53868401", "username": "The Tampa Bay Buccaneers", "betAmount": 5000000, "option": 1}, {"userid": "726b5a5e-9dc0-438e-b6be-fb901a51f482", "username": "Bombshell Blondes Banking", "betAmount": 1000000000, "option": 1}, {"userid": "708be5de-6f82-4353-8d4c-892c1626512e", "username": "IKZ", "betAmount": 25000000, "option": 1}, {"userid": "6846174a-8250-44ee-90eb-dc2e2ea1ffc9", "username": "mette", "betAmount": 500000000, "option": 1}, {"userid": "463fc6c2-201d-4dbc-a35b-0e6960c2ec89", "username": "AltoWalker", "betAmount": 5000000000, "option": 1}, {"userid": "d151de00-6642-4807-8db7-615be63c0103", "username": "skeleturtle-2", "betAmount": 20000000, "option": 1}]}}, "a62dcf37-cdf1-4750-9dc3-0046f6030e3e": {"id": "a62dcf37-cdf1-4750-9dc3-0046f6030e3e", "topic": "Ogey Calibur - Day 1 - Group 3 Winner", "open": false, "winOption": 0, "totalPool": 10101300000, "closingTime": 1715361000000, "options": [{"optionid": 0, "option": "GamersXBreak - [/doog/, /mion/, /nepolabo/, /become/, /fbk/]"}, {"optionid": 1, "option": "Avtism - [/hfz/, /vtwbg/, /nasfaqg/, /fig/, /news/]"}], "userBets": {"0": [{"userid": "726b5a5e-9dc0-438e-b6be-fb901a51f482", "username": "Bombshell Blondes Banking", "betAmount": 50000000, "option": 0}, {"userid": "708be5de-6f82-4353-8d4c-892c1626512e", "username": "IKZ", "betAmount": 46000000, "option": 0}, {"userid": "8b16c5d9-1d06-467c-9c85-eea8d4bf7f68", "username": "Takoside", "betAmount": 5000000000, "option": 0}], "1": [{"userid": "e2f158e4-b22e-4562-9236-a11aab56c20e", "username": "TFRBATTLERISGAY", "betAmount": 5000000, "option": 1}, {"userid": "55b4cbff-bbe8-4061-9ff2-194f53868401", "username": "The Tampa Bay Buccaneers", "betAmount": 5000000000, "option": 1}, {"userid": "8c7fbc0d-0ec8-43ea-b904-bb3b1f1971c4", "username": "★Shariff★", "betAmount": 300000, "option": 1}]}}, "ef20c588-20a5-46fb-83f6-4e85215ced3f": {"id": "ef20c588-20a5-46fb-83f6-4e85215ced3f", "topic": "Ogey Calibur - Day 1 - Group 5 Winner", "open": false, "winOption": 1, "totalPool": 520000000, "closingTime": 1715369640000, "options": [{"optionid": 0, "option": "M.A.A.Y.B. - [/mans/, /stars/, /haha/, /mint/, /yamu/]"}, {"optionid": 1, "option": "Phase Coffee - [/jong/, Lia From Phase Connect, /pcgia/, /pcgen3k/, /fvr/]"}], "userBets": {"0": [], "1": [{"userid": "726b5a5e-9dc0-438e-b6be-fb901a51f482", "username": "Bombshell Blondes Banking", "betAmount": 500000000, "option": 1}, {"userid": "d151de00-6642-4807-8db7-615be63c0103", "username": "skeleturtle-2", "betAmount": 20000000, "option": 1}]}}, "d07feea5-81d0-4db8-93a1-197195948610": {"id": "d07feea5-81d0-4db8-93a1-197195948610", "topic": "Ogey Calibur - Day 2 - Group 4 Winner", "open": false, "winOption": 1, "totalPool": 26139909090, "closingTime": 1715436000000, "options": [{"optionid": 0, "option": "South East Rrats - [/warkop/, Anya Global, Anya-Petra Global, /mep/, /rrat/]"}, {"optionid": 1, "option": "{{{BIGGER}}} - [/vtai/, /swarm/, /wAIfu/, /ag/, /hag/]"}], "userBets": {"0": [{"userid": "8b16c5d9-1d06-467c-9c85-eea8d4bf7f68", "username": "Takoside", "betAmount": 5000000000, "option": 0}, {"userid": "b26dabe8-0cfd-4881-8149-dda45a843af8", "username": "joshukun", "betAmount": 5454545, "option": 0}, {"userid": "8a45cc0b-1717-4c8c-9ac9-90021d076463", "username": "Kuro_Pantsu", "betAmount": 5000000, "option": 0}, {"userid": "340d2c3b-29b6-48a0-9c85-fe3e740dbd60", "username": "[HFZ] ELFS999", "betAmount": 5000000, "option": 0}, {"userid": "6595aa93-8d64-4894-84b0-249a275a7049", "username": "[永] Collective Onobot Fund", "betAmount": 5000000000, "option": 0}, {"userid": "1da7c649-ade5-4538-8605-17c4a6fe6cae", "username": "butwhy...afk", "betAmount": 5000000000, "option": 0}], "1": [{"userid": "55b4cbff-bbe8-4061-9ff2-194f53868401", "username": "The Tampa Bay Buccaneers", "betAmount": 5000000000, "option": 1}, {"userid": "726b5a5e-9dc0-438e-b6be-fb901a51f482", "username": "Bombshell Blondes Banking", "betAmount": 1000000000, "option": 1}, {"userid": "708be5de-6f82-4353-8d4c-892c1626512e", "username": "IKZ", "betAmount": 25000000, "option": 1}, {"userid": "e2f158e4-b22e-4562-9236-a11aab56c20e", "username": "TFRBATTLERISGAY", "betAmount": 5000000, "option": 1}, {"userid": "463fc6c2-201d-4dbc-a35b-0e6960c2ec89", "username": "AltoWalker", "betAmount": 5000000000, "option": 1}, {"userid": "d151de00-6642-4807-8db7-615be63c0103", "username": "skeleturtle-2", "betAmount": 50000000, "option": 1}, {"userid": "79c5aa12-d3e9-49aa-9b63-5cd3bb5c7e33", "username": "BeerSalad", "betAmount": 35000000, "option": 1}, {"userid": "b26dabe8-0cfd-4881-8149-dda45a843af8", "username": "joshukun", "betAmount": 5454545, "option": 1}, {"userid": "6e42912f-8398-4097-ab3f-6826796c8999", "username": "Reverse", "betAmount": 3000000, "option": 1}, {"userid": "355a1840-12eb-41e4-9252-fa12178ababa", "username": "MegaByte", "betAmount": 1000000, "option": 1}]}}, "1353df3b-bc87-4a45-9e29-6b4d1177344c": {"id": "1353df3b-bc87-4a45-9e29-6b4d1177344c", "topic": "Ogey Calibur - Day 2 - Group 5 Winner", "open": false, "winOption": 1, "totalPool": 21641444443, "closingTime": 1715439600000, "options": [{"optionid": 0, "option": "Pink - [/pink/, /holox/, /mayo/, /naa/, /morig/]"}, {"optionid": 1, "option": "The Overlaps - [/wah/, Amelia Watson Appreciation Thread, The Shiori Novella, /HiRyS/, /who/]"}], "userBets": {"0": [{"userid": "708be5de-6f82-4353-8d4c-892c1626512e", "username": "IKZ", "betAmount": 35000000, "option": 0}, {"userid": "e2f158e4-b22e-4562-9236-a11aab56c20e", "username": "TFRBATTLERISGAY", "betAmount": 5000000, "option": 0}, {"userid": "463fc6c2-201d-4dbc-a35b-0e6960c2ec89", "username": "AltoWalker", "betAmount": 5000000000, "option": 0}, {"userid": "d151de00-6642-4807-8db7-615be63c0103", "username": "skeleturtle-2", "betAmount": 20000000, "option": 0}, {"userid": "b26dabe8-0cfd-4881-8149-dda45a843af8", "username": "joshukun", "betAmount": 54545454, "option": 0}, {"userid": "6e42912f-8398-4097-ab3f-6826796c8999", "username": "Reverse", "betAmount": 500000, "option": 0}, {"userid": "1da7c649-ade5-4538-8605-17c4a6fe6cae", "username": "butwhy...afk", "betAmount": 5000000000, "option": 0}, {"userid": "c05c147b-1c76-4cae-9897-6ed9c391b707", "username": "[永] 3beat", "betAmount": 444444444, "option": 0}, {"userid": "8c7fbc0d-0ec8-43ea-b904-bb3b1f1971c4", "username": "★Shariff★", "betAmount": 500000, "option": 0}, {"userid": "ddf873d8-dae4-4205-a98a-04baefbd081d", "username": "Anon D. Zain", "betAmount": 5000000, "option": 0}], "1": [{"userid": "726b5a5e-9dc0-438e-b6be-fb901a51f482", "username": "Bombshell Blondes Banking", "betAmount": 1000000000, "option": 1}, {"userid": "708be5de-6f82-4353-8d4c-892c1626512e", "username": "IKZ", "betAmount": 35000000, "option": 1}, {"userid": "79c5aa12-d3e9-49aa-9b63-5cd3bb5c7e33", "username": "BeerSalad", "betAmount": 25000000, "option": 1}, {"userid": "b26dabe8-0cfd-4881-8149-dda45a843af8", "username": "joshukun", "betAmount": 5454545, "option": 1}, {"userid": "8a45cc0b-1717-4c8c-9ac9-90021d076463", "username": "Kuro_Pantsu", "betAmount": 10000000, "option": 1}, {"userid": "55b4cbff-bbe8-4061-9ff2-194f53868401", "username": "The Tampa Bay Buccaneers", "betAmount": 5000000000, "option": 1}, {"userid": "6595aa93-8d64-4894-84b0-249a275a7049", "username": "[永] Collective Onobot Fund", "betAmount": 5000000000, "option": 1}, {"userid": "355a1840-12eb-41e4-9252-fa12178ababa", "username": "MegaByte", "betAmount": 1000000, "option": 1}]}}, "38c9ef9f-6316-43b0-9985-b420ce27f9fd": {"id": "38c9ef9f-6316-43b0-9985-b420ce27f9fd", "topic": "Ogey Calibur - Day 2 - Group 3 Winner", "open": false, "winOption": 1, "totalPool": 6055565535, "closingTime": 1715448180000, "options": [{"optionid": 0, "option": "Who? - [/corpo/, /wvt/, /tsunX/, /NijiEN/, /asp/]"}, {"optionid": 1, "option": "South East Rrats - [/warkop/, Anya Global, Anya-Petra Global, /mep/, /rrat/]"}], "userBets": {"0": [{"userid": "726b5a5e-9dc0-438e-b6be-fb901a51f482", "username": "Bombshell Blondes Banking", "betAmount": 500000000, "option": 0}, {"userid": "355a1840-12eb-41e4-9252-fa12178ababa", "username": "MegaByte", "betAmount": 10000, "option": 0}, {"userid": "708be5de-6f82-4353-8d4c-892c1626512e", "username": "IKZ", "betAmount": 55555535, "option": 0}, {"userid": "c05c147b-1c76-4cae-9897-6ed9c391b707", "username": "[永] 3beat", "betAmount": 500000000, "option": 0}], "1": [{"userid": "55b4cbff-bbe8-4061-9ff2-194f53868401", "username": "The Tampa Bay Buccaneers", "betAmount": 5000000000, "option": 1}]}}, "0f68ab20-9d9b-445c-88ca-02a71688c809": {"id": "0f68ab20-9d9b-445c-88ca-02a71688c809", "topic": "Ogey Calibur - Day 2 - Group 4 Winner", "open": false, "winOption": 1, "totalPool": 1055565555, "closingTime": 1715451480000, "options": [{"optionid": 0, "option": "Pink - [/pink/, /holox/, /mayo/, /naa/, /morig/]"}, {"optionid": 1, "option": "Who? - [/corpo/, /wvt/, /tsunX/, /NijiEN/, /asp/]"}], "userBets": {"0": [{"userid": "355a1840-12eb-41e4-9252-fa12178ababa", "username": "MegaByte", "betAmount": 10000, "option": 0}, {"userid": "726b5a5e-9dc0-438e-b6be-fb901a51f482", "username": "Bombshell Blondes Banking", "betAmount": 500000000, "option": 0}, {"userid": "708be5de-6f82-4353-8d4c-892c1626512e", "username": "IKZ", "betAmount": 55555555, "option": 0}], "1": [{"userid": "726b5a5e-9dc0-438e-b6be-fb901a51f482", "username": "Bombshell Blondes Banking", "betAmount": 500000000, "option": 1}]}}, "fe87582f-6f9b-431b-acab-a79c4905755e": {"id": "fe87582f-6f9b-431b-acab-a79c4905755e", "topic": "Ogey Calibur - Day 2 - Group 4 Winner", "open": false, "winOption": 1, "totalPool": 1515000000, "closingTime": 1715455440000, "options": [{"optionid": 0, "option": "The Overlaps - [/wah/, Amelia Watson Appreciation Thread, The Shiori Novella, /HiRyS/, /who/]"}, {"optionid": 1, "option": "{{{BIGGER}}} - [/vtai/, /swarm/, /wAIfu/, /ag/, /hag/]"}], "userBets": {"0": [{"userid": "726b5a5e-9dc0-438e-b6be-fb901a51f482", "username": "Bombshell Blondes Banking", "betAmount": 750000000, "option": 0}], "1": [{"userid": "79c5aa12-d3e9-49aa-9b63-5cd3bb5c7e33", "username": "BeerSalad", "betAmount": 15000000, "option": 1}, {"userid": "726b5a5e-9dc0-438e-b6be-fb901a51f482", "username": "Bombshell Blondes Banking", "betAmount": 750000000, "option": 1}]}}, "0d6592a0-e2b4-49b0-bd50-99422ed29aa7": {"id": "0d6592a0-e2b4-49b0-bd50-99422ed29aa7", "topic": "Ogey Calibur - Day 2 - Group 5 Winner", "open": false, "winOption": 0, "totalPool": 5614545454, "closingTime": 1715459820000, "options": [{"optionid": 0, "option": "{{{BIGGER}}} - [/vtai/, /swarm/, /wAIfu/, /ag/, /hag/]"}, {"optionid": 1, "option": "Who? - [/corpo/, /wvt/, /tsunX/, /NijiEN/, /asp/]"}], "userBets": {"0": [{"userid": "d151de00-6642-4807-8db7-615be63c0103", "username": "skeleturtle-2", "betAmount": 50000000, "option": 0}, {"userid": "55b4cbff-bbe8-4061-9ff2-194f53868401", "username": "The Tampa Bay Buccaneers", "betAmount": 5000000000, "option": 0}], "1": [{"userid": "726b5a5e-9dc0-438e-b6be-fb901a51f482", "username": "Bombshell Blondes Banking", "betAmount": 500000000, "option": 1}, {"userid": "8a45cc0b-1717-4c8c-9ac9-90021d076463", "username": "Kuro_Pantsu", "betAmount": 10000000, "option": 1}, {"userid": "b26dabe8-0cfd-4881-8149-dda45a843af8", "username": "joshukun", "betAmount": 54545454, "option": 1}]}}}