{"04e675f1-9668-4f30-82a3-c65789f68863": {"id": "04e675f1-9668-4f30-82a3-c65789f68863", "topic": "Lord of the Board 3 - Day 1 - Match 1 - People's Champion Title Match", "open": false, "winOption": 0, "totalPool": 517555555, "closingTime": 1730567700000, "options": [{"optionid": 0, "option": "/haha/"}, {"optionid": 1, "option": "/lig/ (current champion)"}], "userBets": {"0": [{"userid": "e2f158e4-b22e-4562-9236-a11aab56c20e", "username": "TFRBATTLERISGAY", "betAmount": 5000000, "option": 0}, {"userid": "726b5a5e-9dc0-438e-b6be-fb901a51f482", "username": "Bombshell Blondes Banking", "betAmount": 250000000, "option": 0}], "1": [{"userid": "f467b1e6-b9f2-4c86-ac4a-e79186a214a9", "username": "sanQ", "betAmount": 50000000, "option": 1}, {"userid": "708be5de-6f82-4353-8d4c-892c1626512e", "username": "IKZ", "betAmount": 55555555, "option": 1}, {"userid": "6846174a-8250-44ee-90eb-dc2e2ea1ffc9", "username": "mette", "betAmount": 87000000, "option": 1}, {"userid": "79c5aa12-d3e9-49aa-9b63-5cd3bb5c7e33", "username": "BeerSalad", "betAmount": 40000000, "option": 1}, {"userid": "8a45cc0b-1717-4c8c-9ac9-90021d076463", "username": "Kuro_Pantsu", "betAmount": 30000000, "option": 1}]}}, "d0c3a54e-bb57-4192-a9ef-d48fe2352984": {"id": "d0c3a54e-bb57-4192-a9ef-d48fe2352984", "topic": "Lord of the Board 3 - Day 1 - Match 2 - Group A", "open": false, "winOption": 1, "totalPool": 610555555, "closingTime": 1730569500000, "options": [{"optionid": 0, "option": "/gem/"}, {"optionid": 1, "option": "/fig/"}, {"optionid": 2, "option": "Draw"}], "userBets": {"0": [{"userid": "f467b1e6-b9f2-4c86-ac4a-e79186a214a9", "username": "sanQ", "betAmount": 100000000, "option": 0}, {"userid": "708be5de-6f82-4353-8d4c-892c1626512e", "username": "IKZ", "betAmount": 55555555, "option": 0}, {"userid": "79c5aa12-d3e9-49aa-9b63-5cd3bb5c7e33", "username": "BeerSalad", "betAmount": 40000000, "option": 0}, {"userid": "d151de00-6642-4807-8db7-615be63c0103", "username": "skeleturtle-2", "betAmount": 50000000, "option": 0}], "1": [{"userid": "e2f158e4-b22e-4562-9236-a11aab56c20e", "username": "TFRBATTLERISGAY", "betAmount": 5000000, "option": 1}, {"userid": "726b5a5e-9dc0-438e-b6be-fb901a51f482", "username": "Bombshell Blondes Banking", "betAmount": 250000000, "option": 1}, {"userid": "10be6ad4-b543-4491-b583-735eda2fdbee", "username": "towasamarich", "betAmount": 50000000, "option": 1}], "2": [{"userid": "79c5aa12-d3e9-49aa-9b63-5cd3bb5c7e33", "username": "BeerSalad", "betAmount": 15000000, "option": 2}, {"userid": "8a45cc0b-1717-4c8c-9ac9-90021d076463", "username": "Kuro_Pantsu", "betAmount": 25000000, "option": 2}, {"userid": "10be6ad4-b543-4491-b583-735eda2fdbee", "username": "towasamarich", "betAmount": 20000000, "option": 2}]}}, "850d40cd-0124-46ab-bfdb-30522800da68": {"id": "850d40cd-0124-46ab-bfdb-30522800da68", "topic": "Lord of the Board 3 - Day 1 - Match 3 - Group A", "open": false, "winOption": 0, "totalPool": 825555555, "closingTime": 1730570700000, "options": [{"optionid": 0, "option": "/swarm/"}, {"optionid": 1, "option": "/数字/"}, {"optionid": 2, "option": "Draw"}], "userBets": {"0": [{"userid": "f467b1e6-b9f2-4c86-ac4a-e79186a214a9", "username": "sanQ", "betAmount": 100000000, "option": 0}, {"userid": "e2f158e4-b22e-4562-9236-a11aab56c20e", "username": "TFRBATTLERISGAY", "betAmount": 5000000, "option": 0}, {"userid": "708be5de-6f82-4353-8d4c-892c1626512e", "username": "IKZ", "betAmount": 55555555, "option": 0}, {"userid": "6846174a-8250-44ee-90eb-dc2e2ea1ffc9", "username": "mette", "betAmount": 50000000, "option": 0}, {"userid": "8a45cc0b-1717-4c8c-9ac9-90021d076463", "username": "Kuro_Pantsu", "betAmount": 30000000, "option": 0}, {"userid": "d151de00-6642-4807-8db7-615be63c0103", "username": "skeleturtle-2", "betAmount": 200000000, "option": 0}], "1": [{"userid": "726b5a5e-9dc0-438e-b6be-fb901a51f482", "username": "Bombshell Blondes Banking", "betAmount": 250000000, "option": 1}, {"userid": "79c5aa12-d3e9-49aa-9b63-5cd3bb5c7e33", "username": "BeerSalad", "betAmount": 30000000, "option": 1}, {"userid": "10be6ad4-b543-4491-b583-735eda2fdbee", "username": "towasamarich", "betAmount": 50000000, "option": 1}, {"userid": "8c7fbc0d-0ec8-43ea-b904-bb3b1f1971c4", "username": "★Shariff★", "betAmount": 10000000, "option": 1}], "2": [{"userid": "79c5aa12-d3e9-49aa-9b63-5cd3bb5c7e33", "username": "BeerSalad", "betAmount": 15000000, "option": 2}, {"userid": "10be6ad4-b543-4491-b583-735eda2fdbee", "username": "towasamarich", "betAmount": 20000000, "option": 2}, {"userid": "8c7fbc0d-0ec8-43ea-b904-bb3b1f1971c4", "username": "★Shariff★", "betAmount": 10000000, "option": 2}]}}, "007126cf-4f66-4364-8a9f-4a4b199a330b": {"id": "007126cf-4f66-4364-8a9f-4a4b199a330b", "topic": "Lord of the Board 3 - Day 1 - Match 4 - Group A", "open": false, "winOption": 0, "totalPool": 795555555, "closingTime": 1730571900000, "options": [{"optionid": 0, "option": "/vsinger/"}, {"optionid": 1, "option": "Anya-Petra Global"}, {"optionid": 2, "option": "Draw"}], "userBets": {"0": [{"userid": "f467b1e6-b9f2-4c86-ac4a-e79186a214a9", "username": "sanQ", "betAmount": 100000000, "option": 0}, {"userid": "e2f158e4-b22e-4562-9236-a11aab56c20e", "username": "TFRBATTLERISGAY", "betAmount": 5000000, "option": 0}, {"userid": "708be5de-6f82-4353-8d4c-892c1626512e", "username": "IKZ", "betAmount": 55555555, "option": 0}, {"userid": "8a45cc0b-1717-4c8c-9ac9-90021d076463", "username": "Kuro_Pantsu", "betAmount": 50000000, "option": 0}, {"userid": "d151de00-6642-4807-8db7-615be63c0103", "username": "skeleturtle-2", "betAmount": 200000000, "option": 0}, {"userid": "10be6ad4-b543-4491-b583-735eda2fdbee", "username": "towasamarich", "betAmount": 50000000, "option": 0}], "1": [{"userid": "726b5a5e-9dc0-438e-b6be-fb901a51f482", "username": "Bombshell Blondes Banking", "betAmount": 250000000, "option": 1}, {"userid": "79c5aa12-d3e9-49aa-9b63-5cd3bb5c7e33", "username": "BeerSalad", "betAmount": 30000000, "option": 1}, {"userid": "8c7fbc0d-0ec8-43ea-b904-bb3b1f1971c4", "username": "★Shariff★", "betAmount": 10000000, "option": 1}], "2": [{"userid": "79c5aa12-d3e9-49aa-9b63-5cd3bb5c7e33", "username": "BeerSalad", "betAmount": 15000000, "option": 2}, {"userid": "10be6ad4-b543-4491-b583-735eda2fdbee", "username": "towasamarich", "betAmount": 20000000, "option": 2}, {"userid": "8c7fbc0d-0ec8-43ea-b904-bb3b1f1971c4", "username": "★Shariff★", "betAmount": 10000000, "option": 2}]}}, "d0b57b35-27bf-426e-b13a-7ecbe0d59882": {"id": "d0b57b35-27bf-426e-b13a-7ecbe0d59882", "topic": "Lord of the Board 3 - Day 1 - Match 5 - Group A", "open": false, "winOption": 1, "totalPool": 565555555, "closingTime": 1730573100000, "options": [{"optionid": 0, "option": "/ねぽらぼ/"}, {"optionid": 1, "option": "/vtes/"}, {"optionid": 2, "option": "Draw"}], "userBets": {"0": [{"userid": "f467b1e6-b9f2-4c86-ac4a-e79186a214a9", "username": "sanQ", "betAmount": 50000000, "option": 0}, {"userid": "e2f158e4-b22e-4562-9236-a11aab56c20e", "username": "TFRBATTLERISGAY", "betAmount": 5000000, "option": 0}, {"userid": "708be5de-6f82-4353-8d4c-892c1626512e", "username": "IKZ", "betAmount": 55555555, "option": 0}, {"userid": "8c7fbc0d-0ec8-43ea-b904-bb3b1f1971c4", "username": "★Shariff★", "betAmount": 10000000, "option": 0}, {"userid": "8a45cc0b-1717-4c8c-9ac9-90021d076463", "username": "Kuro_Pantsu", "betAmount": 25000000, "option": 0}], "1": [{"userid": "726b5a5e-9dc0-438e-b6be-fb901a51f482", "username": "Bombshell Blondes Banking", "betAmount": 250000000, "option": 1}, {"userid": "79c5aa12-d3e9-49aa-9b63-5cd3bb5c7e33", "username": "BeerSalad", "betAmount": 30000000, "option": 1}, {"userid": "10be6ad4-b543-4491-b583-735eda2fdbee", "username": "towasamarich", "betAmount": 40000000, "option": 1}], "2": [{"userid": "79c5aa12-d3e9-49aa-9b63-5cd3bb5c7e33", "username": "BeerSalad", "betAmount": 20000000, "option": 2}, {"userid": "d151de00-6642-4807-8db7-615be63c0103", "username": "skeleturtle-2", "betAmount": 50000000, "option": 2}, {"userid": "8c7fbc0d-0ec8-43ea-b904-bb3b1f1971c4", "username": "★Shariff★", "betAmount": 10000000, "option": 2}, {"userid": "10be6ad4-b543-4491-b583-735eda2fdbee", "username": "towasamarich", "betAmount": 20000000, "option": 2}]}}, "23260908-8bad-4fdc-84a5-ecf049f1b257": {"id": "23260908-8bad-4fdc-84a5-ecf049f1b257", "topic": "Lord of the Board 3 - Day 1 - Match 6 - Group A", "open": false, "winOption": 2, "totalPool": 566055555, "closingTime": 1730574300000, "options": [{"optionid": 0, "option": "The Shiori Novella"}, {"optionid": 1, "option": "/vnug/"}, {"optionid": 2, "option": "Draw"}], "userBets": {"0": [{"userid": "f467b1e6-b9f2-4c86-ac4a-e79186a214a9", "username": "sanQ", "betAmount": 150000000, "option": 0}, {"userid": "e2f158e4-b22e-4562-9236-a11aab56c20e", "username": "TFRBATTLERISGAY", "betAmount": 500000, "option": 0}, {"userid": "8c7fbc0d-0ec8-43ea-b904-bb3b1f1971c4", "username": "★Shariff★", "betAmount": 10000000, "option": 0}], "1": [{"userid": "708be5de-6f82-4353-8d4c-892c1626512e", "username": "IKZ", "betAmount": 55555555, "option": 1}, {"userid": "79c5aa12-d3e9-49aa-9b63-5cd3bb5c7e33", "username": "BeerSalad", "betAmount": 45000000, "option": 1}, {"userid": "8c7fbc0d-0ec8-43ea-b904-bb3b1f1971c4", "username": "★Shariff★", "betAmount": 10000000, "option": 1}, {"userid": "8a45cc0b-1717-4c8c-9ac9-90021d076463", "username": "Kuro_Pantsu", "betAmount": 25000000, "option": 1}], "2": [{"userid": "726b5a5e-9dc0-438e-b6be-fb901a51f482", "username": "Bombshell Blondes Banking", "betAmount": 250000000, "option": 2}, {"userid": "10be6ad4-b543-4491-b583-735eda2fdbee", "username": "towasamarich", "betAmount": 20000000, "option": 2}]}}, "1755aaa8-d81d-457b-a654-5a083eb244fb": {"id": "1755aaa8-d81d-457b-a654-5a083eb244fb", "topic": "Lord of the Board 3 - Day 1 - Match 7 - Group E", "open": false, "winOption": 0, "totalPool": 710555555, "closingTime": 1730576400000, "options": [{"optionid": 0, "option": "/mion/"}, {"optionid": 1, "option": "/ss/"}, {"optionid": 2, "option": "Draw"}], "userBets": {"0": [{"userid": "e2f158e4-b22e-4562-9236-a11aab56c20e", "username": "TFRBATTLERISGAY", "betAmount": 5000000, "option": 0}, {"userid": "708be5de-6f82-4353-8d4c-892c1626512e", "username": "IKZ", "betAmount": 55555555, "option": 0}, {"userid": "79c5aa12-d3e9-49aa-9b63-5cd3bb5c7e33", "username": "BeerSalad", "betAmount": 50000000, "option": 0}, {"userid": "8c7fbc0d-0ec8-43ea-b904-bb3b1f1971c4", "username": "★Shariff★", "betAmount": 10000000, "option": 0}, {"userid": "8a45cc0b-1717-4c8c-9ac9-90021d076463", "username": "Kuro_Pantsu", "betAmount": 50000000, "option": 0}], "1": [{"userid": "f467b1e6-b9f2-4c86-ac4a-e79186a214a9", "username": "sanQ", "betAmount": 100000000, "option": 1}, {"userid": "79c5aa12-d3e9-49aa-9b63-5cd3bb5c7e33", "username": "BeerSalad", "betAmount": 50000000, "option": 1}, {"userid": "8c7fbc0d-0ec8-43ea-b904-bb3b1f1971c4", "username": "★Shariff★", "betAmount": 10000000, "option": 1}, {"userid": "10be6ad4-b543-4491-b583-735eda2fdbee", "username": "towasamarich", "betAmount": 80000000, "option": 1}], "2": [{"userid": "726b5a5e-9dc0-438e-b6be-fb901a51f482", "username": "Bombshell Blondes Banking", "betAmount": 250000000, "option": 2}, {"userid": "10be6ad4-b543-4491-b583-735eda2fdbee", "username": "towasamarich", "betAmount": 50000000, "option": 2}]}}, "39e4e1a2-f8f5-44ea-8edc-7556d9a64d56": {"id": "39e4e1a2-f8f5-44ea-8edc-7556d9a64d56", "topic": "Lord of the Board 3 - Day 1 - Match 8 - Group B", "open": false, "winOption": 2, "totalPool": 560555555, "closingTime": 1730577600000, "options": [{"optionid": 0, "option": "/fbk/"}, {"optionid": 1, "option": "/mayo/"}, {"optionid": 2, "option": "Draw"}], "userBets": {"0": [{"userid": "f467b1e6-b9f2-4c86-ac4a-e79186a214a9", "username": "sanQ", "betAmount": 50000000, "option": 0}, {"userid": "79c5aa12-d3e9-49aa-9b63-5cd3bb5c7e33", "username": "BeerSalad", "betAmount": 50000000, "option": 0}, {"userid": "8c7fbc0d-0ec8-43ea-b904-bb3b1f1971c4", "username": "★Shariff★", "betAmount": 10000000, "option": 0}], "1": [{"userid": "e2f158e4-b22e-4562-9236-a11aab56c20e", "username": "TFRBATTLERISGAY", "betAmount": 5000000, "option": 1}, {"userid": "708be5de-6f82-4353-8d4c-892c1626512e", "username": "IKZ", "betAmount": 55555555, "option": 1}, {"userid": "79c5aa12-d3e9-49aa-9b63-5cd3bb5c7e33", "username": "BeerSalad", "betAmount": 50000000, "option": 1}, {"userid": "8c7fbc0d-0ec8-43ea-b904-bb3b1f1971c4", "username": "★Shariff★", "betAmount": 10000000, "option": 1}, {"userid": "d151de00-6642-4807-8db7-615be63c0103", "username": "skeleturtle-2", "betAmount": 80000000, "option": 1}], "2": [{"userid": "726b5a5e-9dc0-438e-b6be-fb901a51f482", "username": "Bombshell Blondes Banking", "betAmount": 250000000, "option": 2}]}}, "67315158-10ec-42c9-bb0e-7f9c2702d63b": {"id": "67315158-10ec-42c9-bb0e-7f9c2702d63b", "topic": "Lord of the Board 3 - Day 1 - Match 9 - Group B", "open": false, "winOption": 2, "totalPool": 3270000000, "closingTime": 1730578800000, "options": [{"optionid": 0, "option": "/v4m/"}, {"optionid": 1, "option": "/hfz/"}, {"optionid": 2, "option": "Draw"}], "userBets": {"0": [{"userid": "8c7fbc0d-0ec8-43ea-b904-bb3b1f1971c4", "username": "★Shariff★", "betAmount": 10000000, "option": 0}, {"userid": "10be6ad4-b543-4491-b583-735eda2fdbee", "username": "towasamarich", "betAmount": 750000000, "option": 0}, {"userid": "f467b1e6-b9f2-4c86-ac4a-e79186a214a9", "username": "sanQ", "betAmount": 100000000, "option": 0}], "1": [{"userid": "708be5de-6f82-4353-8d4c-892c1626512e", "username": "IKZ", "betAmount": 500000000, "option": 1}, {"userid": "6846174a-8250-44ee-90eb-dc2e2ea1ffc9", "username": "mette", "betAmount": 50000000, "option": 1}, {"userid": "79c5aa12-d3e9-49aa-9b63-5cd3bb5c7e33", "username": "BeerSalad", "betAmount": 50000000, "option": 1}, {"userid": "10be6ad4-b543-4491-b583-735eda2fdbee", "username": "towasamarich", "betAmount": 500000000, "option": 1}], "2": [{"userid": "8c7fbc0d-0ec8-43ea-b904-bb3b1f1971c4", "username": "★Shariff★", "betAmount": 10000000, "option": 2}, {"userid": "d151de00-6642-4807-8db7-615be63c0103", "username": "skeleturtle-2", "betAmount": 50000000, "option": 2}, {"userid": "10be6ad4-b543-4491-b583-735eda2fdbee", "username": "towasamarich", "betAmount": 1000000000, "option": 2}, {"userid": "726b5a5e-9dc0-438e-b6be-fb901a51f482", "username": "Bombshell Blondes Banking", "betAmount": 250000000, "option": 2}]}}, "99c60dac-bcc2-49a6-a939-47435d7ce442": {"id": "99c60dac-bcc2-49a6-a939-47435d7ce442", "topic": "Lord of the Board 3 - Day 1 - Match 10 - Group B", "open": false, "winOption": 1, "totalPool": 675555555, "closingTime": 1730580000000, "options": [{"optionid": 0, "option": "Amelia Watson Appreciation Thread"}, {"optionid": 1, "option": "/flip/"}, {"optionid": 2, "option": "Draw"}], "userBets": {"0": [{"userid": "726b5a5e-9dc0-438e-b6be-fb901a51f482", "username": "Bombshell Blondes Banking", "betAmount": 250000000, "option": 0}, {"userid": "79c5aa12-d3e9-49aa-9b63-5cd3bb5c7e33", "username": "BeerSalad", "betAmount": 30000000, "option": 0}], "1": [{"userid": "f467b1e6-b9f2-4c86-ac4a-e79186a214a9", "username": "sanQ", "betAmount": 100000000, "option": 1}, {"userid": "708be5de-6f82-4353-8d4c-892c1626512e", "username": "IKZ", "betAmount": 55555555, "option": 1}, {"userid": "8c7fbc0d-0ec8-43ea-b904-bb3b1f1971c4", "username": "★Shariff★", "betAmount": 10000000, "option": 1}, {"userid": "d151de00-6642-4807-8db7-615be63c0103", "username": "skeleturtle-2", "betAmount": 200000000, "option": 1}], "2": [{"userid": "e2f158e4-b22e-4562-9236-a11aab56c20e", "username": "TFRBATTLERISGAY", "betAmount": 5000000, "option": 2}, {"userid": "79c5aa12-d3e9-49aa-9b63-5cd3bb5c7e33", "username": "BeerSalad", "betAmount": 15000000, "option": 2}, {"userid": "8c7fbc0d-0ec8-43ea-b904-bb3b1f1971c4", "username": "★Shariff★", "betAmount": 10000000, "option": 2}]}}, "e33c4f51-829d-4fd9-94c6-21314f72a22b": {"id": "e33c4f51-829d-4fd9-94c6-21314f72a22b", "topic": "Lord of the Board 3 - Day 1 - Match 11 - Group B", "open": false, "winOption": 0, "totalPool": 640555555, "closingTime": 1730581200000, "options": [{"optionid": 0, "option": "Lia From Phase Connect"}, {"optionid": 1, "option": "/choc/"}, {"optionid": 2, "option": "Draw"}], "userBets": {"0": [{"userid": "e2f158e4-b22e-4562-9236-a11aab56c20e", "username": "TFRBATTLERISGAY", "betAmount": 5000000, "option": 0}, {"userid": "708be5de-6f82-4353-8d4c-892c1626512e", "username": "IKZ", "betAmount": 55555555, "option": 0}, {"userid": "8c7fbc0d-0ec8-43ea-b904-bb3b1f1971c4", "username": "★Shariff★", "betAmount": 10000000, "option": 0}, {"userid": "d151de00-6642-4807-8db7-615be63c0103", "username": "skeleturtle-2", "betAmount": 200000000, "option": 0}], "1": [{"userid": "726b5a5e-9dc0-438e-b6be-fb901a51f482", "username": "Bombshell Blondes Banking", "betAmount": 250000000, "option": 1}, {"userid": "79c5aa12-d3e9-49aa-9b63-5cd3bb5c7e33", "username": "BeerSalad", "betAmount": 40000000, "option": 1}], "2": [{"userid": "f467b1e6-b9f2-4c86-ac4a-e79186a214a9", "username": "sanQ", "betAmount": 50000000, "option": 2}, {"userid": "79c5aa12-d3e9-49aa-9b63-5cd3bb5c7e33", "username": "BeerSalad", "betAmount": 20000000, "option": 2}, {"userid": "8c7fbc0d-0ec8-43ea-b904-bb3b1f1971c4", "username": "★Shariff★", "betAmount": 10000000, "option": 2}]}}, "e4173cc0-b612-4d12-be15-33c92d23b4e7": {"id": "e4173cc0-b612-4d12-be15-33c92d23b4e7", "topic": "Lord of the Board 3 - Day 1 - Match 12 - Group D", "open": false, "winOption": 2, "totalPool": 606555555, "closingTime": 1730582400000, "options": [{"optionid": 0, "option": "/who/"}, {"optionid": 1, "option": "/HAHA/"}, {"optionid": 2, "option": "Draw"}], "userBets": {"0": [{"userid": "f467b1e6-b9f2-4c86-ac4a-e79186a214a9", "username": "sanQ", "betAmount": 50000000, "option": 0}, {"userid": "e2f158e4-b22e-4562-9236-a11aab56c20e", "username": "TFRBATTLERISGAY", "betAmount": 5000000, "option": 0}, {"userid": "9f92d01e-adda-435b-a555-bb89d4b956e6", "username": "HFZArchiveAnon", "betAmount": 1000000, "option": 0}, {"userid": "708be5de-6f82-4353-8d4c-892c1626512e", "username": "IKZ", "betAmount": 55555555, "option": 0}, {"userid": "79c5aa12-d3e9-49aa-9b63-5cd3bb5c7e33", "username": "BeerSalad", "betAmount": 50000000, "option": 0}, {"userid": "8c7fbc0d-0ec8-43ea-b904-bb3b1f1971c4", "username": "★Shariff★", "betAmount": 10000000, "option": 0}], "1": [{"userid": "726b5a5e-9dc0-438e-b6be-fb901a51f482", "username": "Bombshell Blondes Banking", "betAmount": 250000000, "option": 1}, {"userid": "6846174a-8250-44ee-90eb-dc2e2ea1ffc9", "username": "mette", "betAmount": 10000000, "option": 1}, {"userid": "10be6ad4-b543-4491-b583-735eda2fdbee", "username": "towasamarich", "betAmount": 50000000, "option": 1}], "2": [{"userid": "79c5aa12-d3e9-49aa-9b63-5cd3bb5c7e33", "username": "BeerSalad", "betAmount": 15000000, "option": 2}, {"userid": "8c7fbc0d-0ec8-43ea-b904-bb3b1f1971c4", "username": "★Shariff★", "betAmount": 10000000, "option": 2}, {"userid": "10be6ad4-b543-4491-b583-735eda2fdbee", "username": "towasamarich", "betAmount": 100000000, "option": 2}]}}, "72b41858-36c7-414e-8ac2-643e884559d2": {"id": "72b41858-36c7-414e-8ac2-643e884559d2", "topic": "Lord of the Board 3 - Day 1 - Match 13 - Group C", "open": false, "winOption": 1, "totalPool": 695555555, "closingTime": 1730583600000, "options": [{"optionid": 0, "option": "/HiRyS/"}, {"optionid": 1, "option": "/wAIfu/"}, {"optionid": 2, "option": "Draw"}], "userBets": {"0": [{"userid": "e2f158e4-b22e-4562-9236-a11aab56c20e", "username": "TFRBATTLERISGAY", "betAmount": 5000000, "option": 0}, {"userid": "708be5de-6f82-4353-8d4c-892c1626512e", "username": "IKZ", "betAmount": 55555555, "option": 0}, {"userid": "8c7fbc0d-0ec8-43ea-b904-bb3b1f1971c4", "username": "★Shariff★", "betAmount": 10000000, "option": 0}, {"userid": "8a45cc0b-1717-4c8c-9ac9-90021d076463", "username": "Kuro_Pantsu", "betAmount": 60000000, "option": 0}, {"userid": "10be6ad4-b543-4491-b583-735eda2fdbee", "username": "towasamarich", "betAmount": 50000000, "option": 0}], "1": [{"userid": "f467b1e6-b9f2-4c86-ac4a-e79186a214a9", "username": "sanQ", "betAmount": 50000000, "option": 1}, {"userid": "79c5aa12-d3e9-49aa-9b63-5cd3bb5c7e33", "username": "BeerSalad", "betAmount": 50000000, "option": 1}, {"userid": "8c7fbc0d-0ec8-43ea-b904-bb3b1f1971c4", "username": "★Shariff★", "betAmount": 10000000, "option": 1}, {"userid": "d151de00-6642-4807-8db7-615be63c0103", "username": "skeleturtle-2", "betAmount": 80000000, "option": 1}], "2": [{"userid": "726b5a5e-9dc0-438e-b6be-fb901a51f482", "username": "Bombshell Blondes Banking", "betAmount": 250000000, "option": 2}, {"userid": "10be6ad4-b543-4491-b583-735eda2fdbee", "username": "towasamarich", "betAmount": 75000000, "option": 2}]}}, "e6886d67-083d-46fc-8235-0b44742b3d1c": {"id": "e6886d67-083d-46fc-8235-0b44742b3d1c", "topic": "Lord of the Board 3 - Day 1 - Match 14 - Group C", "open": false, "winOption": 2, "totalPool": 470555555, "closingTime": 1730584800000, "options": [{"optionid": 0, "option": "/hlgg/"}, {"optionid": 1, "option": "/holoX/"}, {"optionid": 2, "option": "Draw"}], "userBets": {"0": [{"userid": "e2f158e4-b22e-4562-9236-a11aab56c20e", "username": "TFRBATTLERISGAY", "betAmount": 5000000, "option": 0}, {"userid": "708be5de-6f82-4353-8d4c-892c1626512e", "username": "IKZ", "betAmount": 55555555, "option": 0}, {"userid": "8c7fbc0d-0ec8-43ea-b904-bb3b1f1971c4", "username": "★Shariff★", "betAmount": 10000000, "option": 0}, {"userid": "8a45cc0b-1717-4c8c-9ac9-90021d076463", "username": "Kuro_Pantsu", "betAmount": 40000000, "option": 0}], "1": [{"userid": "f467b1e6-b9f2-4c86-ac4a-e79186a214a9", "username": "sanQ", "betAmount": 50000000, "option": 1}, {"userid": "79c5aa12-d3e9-49aa-9b63-5cd3bb5c7e33", "username": "BeerSalad", "betAmount": 50000000, "option": 1}, {"userid": "8c7fbc0d-0ec8-43ea-b904-bb3b1f1971c4", "username": "★Shariff★", "betAmount": 10000000, "option": 1}], "2": [{"userid": "726b5a5e-9dc0-438e-b6be-fb901a51f482", "username": "Bombshell Blondes Banking", "betAmount": 250000000, "option": 2}]}}, "3e68f296-d8cd-4020-87bf-442a5b963a05": {"id": "3e68f296-d8cd-4020-87bf-442a5b963a05", "topic": "Lord of the Board 3 - Day 1 - Match 15 - Main Event - Ambulance Match", "open": false, "winOption": 1, "totalPool": 518555555, "closingTime": 1730586000000, "options": [{"optionid": 0, "option": "/hag/"}, {"optionid": 1, "option": "/ag/"}], "userBets": {"0": [{"userid": "e2f158e4-b22e-4562-9236-a11aab56c20e", "username": "TFRBATTLERISGAY", "betAmount": 5000000, "option": 0}, {"userid": "726b5a5e-9dc0-438e-b6be-fb901a51f482", "username": "Bombshell Blondes Banking", "betAmount": 250000000, "option": 0}, {"userid": "79c5aa12-d3e9-49aa-9b63-5cd3bb5c7e33", "username": "BeerSalad", "betAmount": 40000000, "option": 0}, {"userid": "d151de00-6642-4807-8db7-615be63c0103", "username": "skeleturtle-2", "betAmount": 8000000, "option": 0}], "1": [{"userid": "f467b1e6-b9f2-4c86-ac4a-e79186a214a9", "username": "sanQ", "betAmount": 100000000, "option": 1}, {"userid": "708be5de-6f82-4353-8d4c-892c1626512e", "username": "IKZ", "betAmount": 55555555, "option": 1}, {"userid": "8c7fbc0d-0ec8-43ea-b904-bb3b1f1971c4", "username": "★Shariff★", "betAmount": 10000000, "option": 1}, {"userid": "8a45cc0b-1717-4c8c-9ac9-90021d076463", "username": "Kuro_Pantsu", "betAmount": 50000000, "option": 1}]}}}